Metadata-Version: 2.1
Name: cell-models
Version: 0.0.1
Summary: This package contains cell models and the ability to apply various protocols to them.
Home-page: https://github.com/pypa/sampleproject
Author: Alex Clark
Author-email: apclarkva@gmail.com
License: UNKNOWN
Platform: UNKNOWN
Classifier: Programming Language :: Python :: 3
Classifier: License :: OSI Approved :: MIT License
Classifier: Operating System :: OS Independent
Requires-Python: >=3.6
